setup.py
bottrap/__init__.py
bottrap/admin.py
bottrap/middleware.py
bottrap/models.py
bottrap/tests.py
bottrap/views.py
bottrap.egg-info/PKG-INFO
bottrap.egg-info/SOURCES.txt
bottrap.egg-info/dependency_links.txt
bottrap.egg-info/top_level.txt