Metadata-Version: 1.0
Name: bottrap
Version: 0.3
Summary: Provides a honeypot for bots to digest
Home-page: https://bitbucket.org/freakypie/bottrap
Author: Danemco, LLC
Author-email: john@velocitywebworks.com
License: UNKNOWN
Platform: UNKNOWN
